{
"type": "FeatureCollection",
"name": "UV Terminals",
"crs": { "type": "name", "properties": { "name": "urn:ogc:def:crs:OGC:1.3:CRS84" } },
"xy_coordinate_resolution": 1e-06,
"features": [
{ "type": "Feature", "properties": { "id": null, "Name": "UV Express SM CSJDM", "description": null, "timestamp": null, "begin": null, "end": null, "altitudeMode": null, "tessellate": -1, "extrude": 0, "visibility": -1, "drawOrder": null, "icon": null }, "geometry": { "type": "Point", "coordinates": [ 121.074625, 14.786075, 0.0 ] } },
{ "type": "Feature", "properties": { "id": null, "Name": "UV Express Terminal Fairveiw Terraces", "description": null, "timestamp": null, "begin": null, "end": null, "altitudeMode": null, "tessellate": -1, "extrude": 0, "visibility": -1, "drawOrder": null, "icon": null }, "geometry": { "type": "Point", "coordinates": [ 121.059982, 14.735599, 87.889025 ] } },
{ "type": "Feature", "properties": { "id": null, "Name": "UV Express Terminal Robinson's Fairview", "description": null, "timestamp": null, "begin": null, "end": null, "altitudeMode": null, "tessellate": -1, "extrude": 0, "visibility": -1, "drawOrder": null, "icon": null }, "geometry": { "type": "Point", "coordinates": [ 121.057399, 14.735321, 81.068811 ] } },
{ "type": "Feature", "properties": { "id": null, "Name": "UV Express Terminal Starmall CSJDM", "description": null, "timestamp": null, "begin": null, "end": null, "altitudeMode": null, "tessellate": -1, "extrude": 0, "visibility": -1, "drawOrder": null, "icon": null }, "geometry": { "type": "Point", "coordinates": [ 121.072336, 14.814375, 115.012478 ] } }
]
}
